faker_file_qt.py
faker_file_qt-0.1.4.dist-info/LICENSE.rst
faker_file_qt-0.1.4.dist-info/METADATA
faker_file_qt-0.1.4.dist-info/WHEEL
faker_file_qt-0.1.4.dist-info/entry_points.txt
faker_file_qt-0.1.4.dist-info/top_level.txt
faker_file_qt-0.1.4.dist-info/RECORD
