Metadata-Version: 2.1
Name: faker-file-qt
Version: 0.1.4
Summary: PyQT UI for faker-file.
Home-page: https://github.com/barseghyanartur/faker-file-qt/
Author: Artur Barseghyan
Author-email: artur.barseghyan@gmail.com
License: MIT
Project-URL: Bug Tracker, https://github.com/barseghyanartur/faker-file-qt/issues
Project-URL: Documentation, https://faker-file-qt.readthedocs.io/
Project-URL: Source Code, https://github.com/barseghyanartur/faker-file-qt/
Project-URL: Changelog, https://faker-file-qt.readthedocs.io/en/latest/changelog.html
Keywords: faker-file faker-file-qt
Classifier: Programming Language :: Python :: 3.8
Classifier: Programming Language :: Python :: 3.9
Classifier: Programming Language :: Python :: 3.10
Classifier: Programming Language :: Python :: 3.11
Classifier: Environment :: X11 Applications
Classifier: Environment :: X11 Applications :: Qt
Classifier: License :: OSI Approved :: MIT License
Classifier: Topic :: Software Development :: Testing
Classifier: Intended Audience :: Developers
Classifier: Operating System :: OS Independent
Classifier: Development Status :: 4 - Beta
Requires-Python: >=3.8
License-File: LICENSE.rst
Requires-Dist: Faker
Requires-Dist: faker-file[common] (>=0.17.8)
Requires-Dist: QDarkStyle
Requires-Dist: PyQt5
Requires-Dist: Pillow (<10.0.0)
Provides-Extra: dev
Requires-Dist: black ; extra == 'dev'
Requires-Dist: detect-secrets ; extra == 'dev'
Requires-Dist: doc8 ; extra == 'dev'
Requires-Dist: ipython ; extra == 'dev'
Requires-Dist: isort ; extra == 'dev'
Requires-Dist: ruff ; extra == 'dev'
Requires-Dist: twine ; extra == 'dev'
